tabify/__init__.py
tabify/my_init.py
tabify-1.0.dist-info/DESCRIPTION.rst
tabify-1.0.dist-info/METADATA
tabify-1.0.dist-info/RECORD
tabify-1.0.dist-info/WHEEL
tabify-1.0.dist-info/metadata.json
tabify-1.0.dist-info/top_level.txt
