Metadata-Version: 2.0
Name: tabify
Version: 1.0
Summary: A python module to emulate Kibana's tabify methods
Home-page: https://github.com/nickmaccarthy/python-tabify
Author: Nick MacCarthy
Author-email: nickmaccarthy@gmail.com
License: Apache 2.0
Download-URL: https://github.com/nickmaccarthy/python-tabify/tarball/1.0
Keywords: tabify kibana elaticsearch html table
Platform: UNKNOWN
Classifier: Development Status :: 4 - Beta
Classifier: Intended Audience :: Developers
Classifier: Topic :: Software Development :: Build Tools
Classifier: License :: OSI Approved :: MIT License
Classifier: Programming Language :: Python :: 2.6
Classifier: Programming Language :: Python :: 2.7
Classifier: Programming Language :: Python :: 3
Classifier: Programming Language :: Python :: 3.2
Classifier: Programming Language :: Python :: 3.3
Classifier: Programming Language :: Python :: 3.4
Classifier: Programming Language :: Python :: 3.5
Classifier: Programming Language :: Python :: 3.6
Provides-Extra: dev
Requires-Dist: check-manifest; extra == 'dev'
Provides-Extra: test
Requires-Dist: coverage; extra == 'test'
